ZefroinLibrary/__init__.py
ZefroinLibrary/zfunct.py
ZefroinLibrary-0.0.6.dist-info/METADATA
ZefroinLibrary-0.0.6.dist-info/WHEEL
ZefroinLibrary-0.0.6.dist-info/top_level.txt
ZefroinLibrary-0.0.6.dist-info/RECORD
